rich_torndb/__init__.py
rich_torndb/init_tables.py
rich_torndb/rich_torndb.py
rich_torndb/table_joiner.py
rich_torndb/utils/__init__.py
rich_torndb/utils/changes_log.py
rich_torndb/utils/log_helper.py
rich_torndb/utils/printer.py
rich_torndb/utils/sql_formatter.py
rich_torndb/utils/sql_invalid_errors.py
rich_torndb/utils/sql_valid_checker.py
rich_torndb/utils/torndb.py
rich_torndb-0.0.2.dist-info/LICENSE
rich_torndb-0.0.2.dist-info/METADATA
rich_torndb-0.0.2.dist-info/WHEEL
rich_torndb-0.0.2.dist-info/top_level.txt
rich_torndb-0.0.2.dist-info/RECORD
